bible_male_names/__init__.py
bible_male_names-1.0.1.dist-info/METADATA
bible_male_names-1.0.1.dist-info/RECORD
bible_male_names-1.0.1.dist-info/WHEEL
bible_male_names-1.0.1.dist-info/top_level.txt
