Metadata-Version: 2.1
Name: bible-male-names
Version: 1.0.1
Summary: Get male names from The Bible
Home-page: https://abranhe.com
Author: Carlos Abraham
Author-email: abraham@abranhe.com
License: UNKNOWN
Project-URL: Source, https://github.com/abranhe/bible-male-names.py
Platform: UNKNOWN
Classifier: Programming Language :: Python
Classifier: Natural Language :: English
Classifier: Environment :: Plugins
Classifier: Intended Audience :: Developers
Classifier: License :: OSI Approved :: MIT License
